oscfs/__init__.py
oscfs/fs.py
oscfs/link.py
oscfs/misc.py
oscfs/obs.py
oscfs/obsfile.py
oscfs/package.py
oscfs/project.py
oscfs/refreshtrigger.py
oscfs/root.py
oscfs/types.py
oscfs/urlopenwrapper.py
oscfs-0.7.0.data/scripts/oscfs
oscfs-0.7.0.dist-info/DESCRIPTION.rst
oscfs-0.7.0.dist-info/METADATA
oscfs-0.7.0.dist-info/RECORD
oscfs-0.7.0.dist-info/WHEEL
oscfs-0.7.0.dist-info/metadata.json
oscfs-0.7.0.dist-info/top_level.txt
