Metadata-Version: 2.0
Name: oscfs
Version: 0.7.0
Summary: A FUSE based file system to access Open Build Service (OBS) instances
Home-page: https://github.com/mgerstner/oscfs
Author: Matthias Gerstner
Author-email: matthias.gerstner@suse.de
License: GPL2
Keywords: fuse obs osc openSUSE
Platform: UNKNOWN
Classifier: Intended Audience :: Developers
Classifier: License :: OSI Approved :: GNU General Public License v2 (GPLv2)
Classifier: Programming Language :: Python :: 2.7
Classifier: Topic :: System :: Filesystems
Requires-Dist: fusepy
Requires-Dist: osc
